[{"id":229603,"id_state":984,"text":"Canillo","id_country":145},{"id":229615,"id_state":985,"text":"Encamp","id_country":145},{"id":229630,"id_state":986,"text":"La Maçana","id_country":145},{"id":229631,"id_state":986,"text":"La Massana","id_country":145},{"id":229648,"id_state":987,"text":"Ordino","id_country":145},{"id":229657,"id_state":988,"text":"San Juliá","id_country":145},{"id":229659,"id_state":988,"text":"Santa Juliá de Loria","id_country":145},{"id":229662,"id_state":988,"text":"Sant Juliá","id_country":145},{"id":229663,"id_state":988,"text":"Sant Julià de Lòria","id_country":145},{"id":229588,"id_state":989,"text":"Andorra","id_country":145},{"id":229589,"id_state":989,"text":"Andorra la Vella","id_country":145},{"id":229590,"id_state":989,"text":"Andorra-Vieille","id_country":145},{"id":229591,"id_state":989,"text":"Andorre","id_country":145},{"id":229592,"id_state":989,"text":"Andorre-la-Vieille","id_country":145},{"id":229593,"id_state":989,"text":"Andorre-Vieille","id_country":145},{"id":229633,"id_state":989,"text":"la Vieja","id_country":145},{"id":229621,"id_state":990,"text":"Escaldas","id_country":145},{"id":229622,"id_state":990,"text":"Escaldes","id_country":145},{"id":229632,"id_state":990,"text":"Las Escadas","id_country":145},{"id":229635,"id_state":990,"text":"Les Escaldes","id_country":145}]