[{"id":319342,"id_state":1159,"text":"Hinterer Schellenberg","id_country":126},{"id":319343,"id_state":1159,"text":"Hinter-Schellenberg","id_country":126},{"id":319350,"id_state":1159,"text":"Mittler-Schellenberg","id_country":126},{"id":319351,"id_state":1159,"text":"Mittlerschellenberg","id_country":126},{"id":319363,"id_state":1159,"text":"Schellenberg","id_country":126},{"id":319369,"id_state":1159,"text":"Vorderer Schellenberg","id_country":126},{"id":319371,"id_state":1159,"text":"Vorderschellenberg","id_country":126}]