[{"id":198123,"id_state":960,"text":"Carlsbad","id_country":65},{"id":198428,"id_state":960,"text":"Cheb","id_country":65},{"id":199887,"id_state":960,"text":"Eger","id_country":65},{"id":199974,"id_state":960,"text":"Faiknov","id_country":65},{"id":199976,"id_state":960,"text":"Falkenau","id_country":65},{"id":199977,"id_state":960,"text":"Falkenau an der Eger","id_country":65},{"id":199979,"id_state":960,"text":"Falknov","id_country":65},{"id":199980,"id_state":960,"text":"Falknov nad Ohri","id_country":65},{"id":202509,"id_state":960,"text":"Karlovy Vary","id_country":65},{"id":202521,"id_state":960,"text":"Karl Vary","id_country":65},{"id":210513,"id_state":960,"text":"Sokolov","id_country":65}]